CHANGES.rst
CONTRIBUTORS.rst
MANIFEST.in
README.rst
buildout-bootstrap.py
setup.cfg
setup.py
tests.py
src/ps/__init__.py
src/ps.bob.egg-info/PKG-INFO
src/ps.bob.egg-info/SOURCES.txt
src/ps.bob.egg-info/dependency_links.txt
src/ps.bob.egg-info/not-zip-safe
src/ps.bob.egg-info/requires.txt
src/ps.bob.egg-info/top_level.txt
src/ps/bob/__init__.py
src/ps/bob/hooks.py
src/ps/bob/diazo_theme/.mrbob.ini
src/ps/bob/diazo_theme/+package.dottedname+/.csslintrc
src/ps/bob/diazo_theme/+package.dottedname+/.editorconfig
src/ps/bob/diazo_theme/+package.dottedname+/.gitignore
src/ps/bob/diazo_theme/+package.dottedname+/.jshintignore.bob
src/ps/bob/diazo_theme/+package.dottedname+/.travis.yml
src/ps/bob/diazo_theme/+package.dottedname+/CHANGES.rst
src/ps/bob/diazo_theme/+package.dottedname+/CONTRIBUTORS.rst
src/ps/bob/diazo_theme/+package.dottedname+/README.rst.bob
src/ps/bob/diazo_theme/+package.dottedname+/buildout-bootstrap.py
src/ps/bob/diazo_theme/+package.dottedname+/buildout.cfg.bob
src/ps/bob/diazo_theme/+package.dottedname+/requirements.txt
src/ps/bob/diazo_theme/+package.dottedname+/setup.cfg.bob
src/ps/bob/diazo_theme/+package.dottedname+/setup.py.bob
src/ps/bob/diazo_theme/+package.dottedname+/travis.cfg.bob
src/ps/bob/diazo_theme/+package.dottedname+/docs/README.bob
src/ps/bob/diazo_theme/+package.dottedname+/docs/_images/README.bob
src/ps/bob/diazo_theme/+package.dottedname+/docs/source/conf.py.bob
src/ps/bob/diazo_theme/+package.dottedname+/docs/source/configuration.rst.bob
src/ps/bob/diazo_theme/+package.dottedname+/docs/source/index.rst.bob
src/ps/bob/diazo_theme/+package.dottedname+/docs/source/_static/logo.png
src/ps/bob/diazo_theme/+package.dottedname+/docs/source/_templates/empty
src/ps/bob/diazo_theme/+package.dottedname+/src/+package.namespace+/__init__.py
src/ps/bob/diazo_theme/+package.dottedname+/src/+package.namespace+/+package.namespace2+/__init__.py
src/ps/bob/diazo_theme/+package.dottedname+/src/+package.namespace+/+package.namespace2+/+package.name+/__init__.py.bob
src/ps/bob/diazo_theme/+package.dottedname+/src/+package.namespace+/+package.namespace2+/+package.name+/config.py.bob
