Metadata-Version: 1.1
Name: ps.bob
Version: 0.1.2
Summary: mr.bob templates for Propertyshelf projects.
Home-page: https://github.com/propertyshelf/ps.bob
Author: Propertyshelf, Inc.
Author-email: development@propertyshelf.com
License: BSD
Download-URL: http://pypi.python.org/pypi/ps.bob
Keywords: plone zope diazo skeleton templating
Platform: UNKNOWN
Classifier: Environment :: Console
Classifier: Intended Audience :: Developers
Classifier: License :: OSI Approved :: BSD License
Classifier: Natural Language :: English
Classifier: Operating System :: OS Independent
Classifier: Programming Language :: Python
Classifier: Programming Language :: Python :: 2.6
Classifier: Programming Language :: Python :: 2.7
Classifier: Topic :: Software Development :: Code Generators
Classifier: Topic :: Utilities
